cpanel_api/__init__.py
cpanel_api-0.3.0.dist-info/WHEEL
cpanel_api-0.3.0.dist-info/METADATA
cpanel_api-0.3.0.dist-info/RECORD
