Metadata-Version: 2.1
Name: cpanel-api
Version: 0.3.0
Summary: CPanel API Client. Supports cPanel API 2 and UAPI.
Home-page: https://github.com/tz4678/cpanel-api
Author: Sergey M
Author-email: tz4678@gmail.com
Requires-Python: >=3.8,<4.0
Classifier: Programming Language :: Python :: 3
Classifier: Programming Language :: Python :: 3.8
Classifier: Programming Language :: Python :: 3.9
Classifier: Topic :: Software Development :: Libraries :: Python Modules
Classifier: Topic :: Utilities
Requires-Dist: pysocks (>=1.7.1,<2.0.0)
Requires-Dist: requests (>=2.24.0,<3.0.0)
